README.md
setup.py
taggercore/__init__.py
taggercore.egg-info/PKG-INFO
taggercore.egg-info/SOURCES.txt
taggercore.egg-info/dependency_links.txt
taggercore.egg-info/requires.txt
taggercore.egg-info/top_level.txt
taggercore/config/__init__.py
taggercore/config/config.py
taggercore/config/config_error.py
taggercore/config/credentials.py
taggercore/manipulation/__init__.py
taggercore/manipulation/arn_manipulation_strategy.py
taggercore/manipulation/arn_manipulation_strategy_factory.py
taggercore/manipulation/no_arn_manipulation_strategy.py
taggercore/manipulation/s3_arn_manipulation_strategy.py
taggercore/model/__init__.py
taggercore/model/resource.py
taggercore/model/resource_with_tag_diffs.py
taggercore/model/tag.py
taggercore/model/tag_diff.py
taggercore/model/tag_diff_type.py
taggercore/model/tagging_result.py
taggercore/scanner/__init__.py
taggercore/scanner/global_scanner.py
taggercore/scanner/region_scanner.py
taggercore/scanner/util.py
taggercore/tagger/__init__.py
taggercore/tagger/abstract_resource_group_api_tagger.py
taggercore/tagger/global_tagger.py
taggercore/tagger/iam_tagger.py
taggercore/tagger/region_tagger.py
taggercore/tagger/service_tagger.py
taggercore/tagger/super_tagger.py
taggercore/usecase/__init__.py
taggercore/usecase/configure_account_and_profile.py
taggercore/usecase/fetch_config.py
taggercore/usecase/perform_tagging.py
taggercore/usecase/scan.py
taggercore/usecase/scan_and_compare.py
test/__init__.py
test/conftest.py
test/stubs/__init__.py
test/stubs/core_resource_stubs.py
test/stubs/resource_stub.py
test/tagger/test_global_tagger.py
test/tagger/test_iam_tagger.py
test/tagger/test_region_tagger.py
test/tagger/test_super_tagger.py