Metadata-Version: 2.1
Name: taggercore
Version: 1.0.0
Summary: Provides utility classes for scanning AWS accounts and applying tags to AWS resources
Home-page: https://github.com/IT-EXPERTS-AT/tagger
Author: IT-experts
Author-email: github@it-experts.at
License: License :: OSI Approved :: Apache Software License
Keywords: AWS,AWS tags,CLI,tags,tag,tagging,AWS management
Platform: UNKNOWN
Classifier: Operating System :: OS Independent
Classifier: License :: OSI Approved :: Apache Software License
Classifier: Programming Language :: Python :: 3.8
Provides-Extra: dev
